pythoml/__init__.py
pythoml/html.py
pythoml/tag.py
pythoml-0.1.0.dist-info/METADATA
pythoml-0.1.0.dist-info/WHEEL
pythoml-0.1.0.dist-info/RECORD
