Metadata-Version: 2.3
Name: pythoml
Version: 0.1.0
Summary: Generate HTML with Python
Classifier: Environment :: Web Environment
Classifier: Intended Audience :: Developers
Classifier: License :: OSI Approved :: MIT License
Classifier: Operating System :: OS Independent
Classifier: Programming Language :: Python :: 3
Requires-Python: >=3.12
